MANIFEST.in
README.txt
setup.py
docs/HISTORY.txt
docs/INSTALL.txt
docs/LICENSE.GPL
docs/LICENSE.txt
quintagroup/__init__.py
quintagroup.theme.estatelite.egg-info/PKG-INFO
quintagroup.theme.estatelite.egg-info/SOURCES.txt
quintagroup.theme.estatelite.egg-info/dependency_links.txt
quintagroup.theme.estatelite.egg-info/entry_points.txt
quintagroup.theme.estatelite.egg-info/namespace_packages.txt
quintagroup.theme.estatelite.egg-info/not-zip-safe
quintagroup.theme.estatelite.egg-info/requires.txt
quintagroup.theme.estatelite.egg-info/top_level.txt
quintagroup/theme/__init__.py
quintagroup/theme/estatelite/README.txt
quintagroup/theme/estatelite/__init__.py
quintagroup/theme/estatelite/configure.zcml
quintagroup/theme/estatelite/profiles/default/metadata.xml
quintagroup/theme/estatelite/profiles/default/theme.xml
quintagroup/theme/estatelite/profiles/default/tinymce.xml
quintagroup/theme/estatelite/static/index.html
quintagroup/theme/estatelite/static/manifest.cfg
quintagroup/theme/estatelite/static/rules.xml
quintagroup/theme/estatelite/static/css/IEFixes.css
quintagroup/theme/estatelite/static/css/estatelite.css
quintagroup/theme/estatelite/static/images/album.png
quintagroup/theme/estatelite/static/images/estateLiteLogo.png
quintagroup/theme/estatelite/static/images/estate_lite_sprite.png
quintagroup/theme/estatelite/static/images/favicon.ico
quintagroup/theme/estatelite/static/images/header.jpg
quintagroup/theme/estatelite/static/images/icons-sprite.png